funnelplot/__init__.py
funnelplot/_nbdev.py
funnelplot/core.py
funnelplot-0.2.1.dist-info/LICENSE
funnelplot-0.2.1.dist-info/METADATA
funnelplot-0.2.1.dist-info/WHEEL
funnelplot-0.2.1.dist-info/entry_points.txt
funnelplot-0.2.1.dist-info/top_level.txt
funnelplot-0.2.1.dist-info/RECORD
