Metadata-Version: 2.1
Name: funnelplot
Version: 0.2.1
Summary: Simple funnel plots
Home-page: https://github.com/johnhw/funnelplot
Author: John H. Williamson
Author-email: johnhw@gmail.com
License: MIT License
Keywords: funnel plot
Platform: UNKNOWN
Classifier: Development Status :: 3 - Alpha
Classifier: Intended Audience :: Developers
Classifier: License :: OSI Approved :: MIT License
Classifier: Natural Language :: English
Classifier: Programming Language :: Python :: 3.6
Classifier: Programming Language :: Python :: 3.7
Classifier: Programming Language :: Python :: 3.8
Requires-Python: >=3.6
Requires-Dist: matplotlib
Requires-Dist: numpy
Requires-Dist: scipy
